bt-1.1.2.dist-info/RECORD
bt-1.1.2.dist-info/WHEEL
bt-1.1.2.dist-info/top_level.txt
bt-1.1.2.dist-info/METADATA
bt-1.1.2.dist-info/licenses/LICENSE
bt/algos.py
bt/core.cpython-312-darwin.so
bt/__init__.py
bt/core.py
bt/backtest.py
