Metadata-Version: 2.1
Name: bt
Version: 1.1.2
Summary: A flexible backtesting framework for Python
Home-page: https://github.com/pmorissette/bt
Author: Philippe Morissette
Author-email: morissette.philippe@gmail.com
License: MIT
Keywords: python finance quant backtesting strategies algotrading algorithmic trading
Platform: UNKNOWN
Classifier: Development Status :: 4 - Beta
Classifier: Programming Language :: Python
Classifier: Programming Language :: Python :: 3
Classifier: Programming Language :: Python :: 3.9
Classifier: Programming Language :: Python :: 3.10
Classifier: Programming Language :: Python :: 3.11
Classifier: Programming Language :: Python :: 3.12
Classifier: Programming Language :: Python :: 3.13
Classifier: Topic :: Software Development :: Libraries
Classifier: License :: OSI Approved :: MIT License
Requires-Python: >=3.9
Provides-Extra: dev
License-File: LICENSE
